AGRemapUtils/__init__.py
AGRemapUtils/Utils/Algo.py
AGRemapUtils/Utils/DFSData.py
AGRemapUtils/Utils/FileTools.py
AGRemapUtils/Utils/Heading.py
AGRemapUtils/Utils/TextTools.py
AGRemapUtils/Utils/__init__.py
AGRemapUtils/Utils/commands/BaseCommandBuilder.py
AGRemapUtils/Utils/commands/CommandFormatter.py
AGRemapUtils/Utils/commands/TesterCommandBuilder.py
AGRemapUtils/Utils/commands/__init__.py
AGRemapUtils/Utils/constants/BoilerPlate.py
AGRemapUtils/Utils/constants/FileExts.py
AGRemapUtils/Utils/constants/PathConstants.py
AGRemapUtils/Utils/constants/Paths.py
AGRemapUtils/Utils/constants/StrReplacements.py
AGRemapUtils/Utils/constants/__init__.py
AGRemapUtils/Utils/constants/toolStats.py
AGRemapUtils/Utils/constants/script/KeyWordTypes.py
AGRemapUtils/Utils/constants/script/ScriptKeyWords.py
AGRemapUtils/Utils/enums/ScriptPartNames.py
AGRemapUtils/Utils/enums/StrEnum.py
AGRemapUtils/Utils/enums/SysEnum.py
AGRemapUtils/Utils/enums/__init__.py
AGRemapUtils/Utils/exceptions/Error.py
AGRemapUtils/Utils/exceptions/InvalidCommand.py
AGRemapUtils/Utils/exceptions/InvalidSystem.py
AGRemapUtils/Utils/exceptions/TestError.py
AGRemapUtils/Utils/exceptions/TestExpectedOutputsNotFound.py
AGRemapUtils/Utils/exceptions/TestNoInputsFound.py
AGRemapUtils/Utils/exceptions/TestResultOutputsNotFound.py
AGRemapUtils/Utils/exceptions/TesterFailed.py
AGRemapUtils/Utils/exceptions/__init__.py
AGRemapUtils/Utils/exceptions/script/InvalidKeyWordType.py
AGRemapUtils/Utils/exceptions/script/MissingKeyWord.py
AGRemapUtils/Utils/packageUpdater/BasePackageUpdater.py
AGRemapUtils/Utils/packageUpdater/PipUpdater.py
AGRemapUtils/Utils/packageUpdater/__init__.py
AGRemapUtils/Utils/path/FilePathTools.py
AGRemapUtils/Utils/path/FileTools.py
AGRemapUtils/Utils/path/ModulePathTools.py
AGRemapUtils/Utils/path/PyPathTools.py
AGRemapUtils/Utils/path/PyProjectPathTools.py
AGRemapUtils/Utils/path/__init__.py
AGRemapUtils/Utils/pipeline/Pipeline.py
AGRemapUtils/Utils/pipeline/Stage.py
agremaputils-1.0.5.dist-info/licenses/LICENSE
agremaputils-1.0.5.dist-info/METADATA
agremaputils-1.0.5.dist-info/WHEEL
agremaputils-1.0.5.dist-info/top_level.txt
agremaputils-1.0.5.dist-info/RECORD
