Metadata-Version: 2.4
Name: AGRemapUtils
Version: 1.0.5
Summary: Utility library for the Anime Game Remap (AGRemap) project
Author-email: Albert Gold <AlexXianZhenYuAu@gmail.com>
Project-URL: Homepage, https://github.com/nhok0169/Anime-Game-Remap
Project-URL: Repository, https://github.com/nhok0169/Anime-Game-Remap
Classifier: Programming Language :: Python :: 3
Classifier: License :: OSI Approved :: MIT License
Classifier: Operating System :: OS Independent
Requires-Python: >=3.6
License-File: LICENSE
Requires-Dist: ordered-set>=4.1.0
Requires-Dist: directory-tree>=0.0.4
Dynamic: license-file
